nonebot_plugin_image_symmetry/__init__.py
nonebot_plugin_image_symmetry/command.py
nonebot_plugin_image_symmetry/functions.py
nonebot_plugin_image_symmetry/utils.py
nonebot_plugin_image_symmetry-0.3.1.dist-info/METADATA
nonebot_plugin_image_symmetry-0.3.1.dist-info/WHEEL
nonebot_plugin_image_symmetry-0.3.1.dist-info/licenses/LICENSE
nonebot_plugin_image_symmetry-0.3.1.dist-info/RECORD
