Metadata-Version: 2.4
Name: nonebot-plugin-image-symmetry
Version: 0.3.1
Summary: NoneBot 图像对称处理插件，提供图片上下左右四个方向的对称变换功能
License: Apache-2.0
License-File: LICENSE
Keywords: nonebot,nonebot2,plugin,image-processing
Author: GT610
Author-email: myddz1005@outlook.com
Requires-Python: >=3.9,<4.0
Classifier: License :: OSI Approved :: Apache Software License
Classifier: Programming Language :: Python :: 3
Classifier: Programming Language :: Python :: 3.9
Classifier: Programming Language :: Python :: 3.10
Classifier: Programming Language :: Python :: 3.11
Classifier: Programming Language :: Python :: 3.12
Classifier: Programming Language :: Python :: 3.13
Classifier: Programming Language :: Python :: 3.14
Requires-Dist: nonebot-plugin-alconna (>=0.50.0,<1.0.0)
Requires-Dist: nonebot2 (>=2.3.0,<3.0.0)
Requires-Dist: pillow (>=10.4.0)
Project-URL: Homepage, https://github.com/GT-610/nonebot-plugin-image-symmetry
Project-URL: Repository, https://github.com/GT-610/nonebot-plugin-image-symmetry
